rustpdf_compress/__init__.py
rustpdf_compress/__pycache__/__init__.cpython-314.pyc
rustpdf_compress/rustpdf_compress.abi3.so
rustpdf_compress-2026.1.0.dist-info/METADATA
rustpdf_compress-2026.1.0.dist-info/WHEEL
rustpdf_compress-2026.1.0.dist-info/RECORD
