Metadata-Version: 2.4
Name: rustpdf-compress
Version: 2026.1.0
Classifier: Development Status :: 4 - Beta
Classifier: Intended Audience :: Developers
Classifier: License :: OSI Approved :: MIT License
Classifier: Programming Language :: Python :: 3
Classifier: Programming Language :: Python :: 3.8
Classifier: Programming Language :: Python :: 3.9
Classifier: Programming Language :: Python :: 3.10
Classifier: Programming Language :: Python :: 3.11
Classifier: Programming Language :: Python :: 3.12
Classifier: Programming Language :: Rust
Classifier: Topic :: Multimedia :: Graphics :: Graphics Conversion
Summary: 基于 Rust 的高性能 PDF 压缩库，支持三种压缩级别
Keywords: pdf,压缩,compress,rust
Author-email: Your Name <your@email.com>
License: MIT
Requires-Python: >=3.8
Project-URL: Homepage, https://github.com/yourusername/rustpdf-compress
